[
    {
        "d_p": 36059937,
        "d_s": 24945223,
        "label": 0,
        "sl_max": 4.209,
        "cost_max": 1.187,
        "id": "3d1d67d9618348e88f6d834ff429847d"
    },
    {
        "d_p": 49075663,
        "d_s": 4523738,
        "label": 1,
        "sl_max": 3.915,
        "cost_max": 1.041,
        "id": "840e59fe5f734b54b8550902cb1e7cb4"
    },
    {
        "d_p": 30263412,
        "d_s": 48170764,
        "label": 1,
        "sl_max": 5.601,
        "cost_max": 2.842,
        "id": "86004207eeaa4a4285a04ecb867348cc"
    },
    {
        "d_p": 40982639,
        "d_s": 37957980,
        "label": 1,
        "sl_max": 6.221,
        "cost_max": 2.716,
        "id": "cc4777d2ab1c4fbf911ca7c95234e9a2"
    },
    {
        "d_p": 18061518,
        "d_s": 16614963,
        "label": 0,
        "sl_max": 2.665,
        "cost_max": 1.22,
        "id": "d6f22c25ec934b46aa4a9abeedbdcbb4"
    },
    {
        "d_p": 20029343,
        "d_s": 3760931,
        "label": 0,
        "sl_max": 1.774,
        "cost_max": 0.469,
        "id": "1232be30077349f19bac66ca74e76842"
    },
    {
        "d_p": 41240701,
        "d_s": 39542806,
        "label": 0,
        "sl_max": 4.782,
        "cost_max": 2.571,
        "id": "d9da49d3feb643f28aff5a31b1c388da"
    },
    {
        "d_p": 47470755,
        "d_s": 18168423,
        "label": 1,
        "sl_max": 2.807,
        "cost_max": 1.682,
        "id": "daef16ddc8604c52ab7d883b00acdf5f"
    },
    {
        "d_p": 27601801,
        "d_s": 49836920,
        "label": 1,
        "sl_max": 4.6,
        "cost_max": 2.432,
        "id": "9cbaded45fb24c35a07675ea7ff83f48"
    },
    {
        "d_p": 22670330,
        "d_s": 32664278,
        "label": 0,
        "sl_max": 2.368,
        "cost_max": 1.23,
        "id": "be3af1aeed5b4f8ab2d610f42c655aa6"
    },
    {
        "d_p": 29501593,
        "d_s": 24455091,
        "label": 0,
        "sl_max": 3.864,
        "cost_max": 1.128,
        "id": "d233e474262e4d339fae80f61cc04c77"
    },
    {
        "d_p": 16677172,
        "d_s": 48844720,
        "label": 1,
        "sl_max": 2.754,
        "cost_max": 2.162,
        "id": "3f3646ebce074c448f064ee79f2b7fab"
    },
    {
        "d_p": 40939780,
        "d_s": 36025243,
        "label": 0,
        "sl_max": 3.142,
        "cost_max": 2.625,
        "id": "1d7609fa376f48619cf1d7e6a4125a74"
    },
    {
        "d_p": 21149392,
        "d_s": 33363886,
        "label": 1,
        "sl_max": 3.782,
        "cost_max": 1.497,
        "id": "e13fe0879c534bbb872401a0261e0d49"
    },
    {
        "d_p": 47376894,
        "d_s": 7618284,
        "label": 0,
        "sl_max": 3.974,
        "cost_max": 1.262,
        "id": "85ba5223a18841c3b560682f02bddf74"
    },
    {
        "d_p": 32443229,
        "d_s": 43622940,
        "label": 1,
        "sl_max": 5.956,
        "cost_max": 2.856,
        "id": "8e7b5e168ac64fe290b74bdf59fd0667"
    },
    {
        "d_p": 24698578,
        "d_s": 13878134,
        "label": 1,
        "sl_max": 2.059,
        "cost_max": 1.247,
        "id": "0a26ece9a07a4eb7822fceb55f175a8d"
    },
    {
        "d_p": 9698702,
        "d_s": 21910276,
        "label": 0,
        "sl_max": 1.359,
        "cost_max": 0.947,
        "id": "554d404965aa48f3b810328a180bf071"
    },
    {
        "d_p": 15975248,
        "d_s": 41449133,
        "label": 0,
        "sl_max": 3.281,
        "cost_max": 2.056,
        "id": "c6fe72f37e3042b4841afca963c2f455"
    },
    {
        "d_p": 9067357,
        "d_s": 21773202,
        "label": 0,
        "sl_max": 2.213,
        "cost_max": 0.93,
        "id": "498ebdc3d57a4d858fff322799b5663b"
    },
    {
        "d_p": 21103636,
        "d_s": 28822284,
        "label": 1,
        "sl_max": 3.291,
        "cost_max": 1.799,
        "id": "63ae0e10b39e4dd38aeeaa761f7ad2fd"
    },
    {
        "d_p": 36796452,
        "d_s": 23704985,
        "label": 1,
        "sl_max": 2.509,
        "cost_max": 1.369,
        "id": "8cd80a4470414cb8ab39669a4f5f488f"
    },
    {
        "d_p": 2925270,
        "d_s": 27364998,
        "label": 0,
        "sl_max": 2.254,
        "cost_max": 0.806,
        "id": "394a6378e7394771a9f85c18a485d38b"
    },
    {
        "d_p": 35667443,
        "d_s": 24431334,
        "label": 1,
        "sl_max": 4.6,
        "cost_max": 1.439,
        "id": "01ffbb8d3b134d01b693dbf4813e0e8e"
    },
    {
        "d_p": 7231131,
        "d_s": 3100255,
        "label": 0,
        "sl_max": 0.558,
        "cost_max": 0.336,
        "id": "b1f088d8319641d1ad61a45f396c9a48"
    },
    {
        "d_p": 35513735,
        "d_s": 12690805,
        "label": 1,
        "sl_max": 3.134,
        "cost_max": 1.453,
        "id": "946c80bfadd5443fb7f6d354f75dd50e"
    },
    {
        "d_p": 15804227,
        "d_s": 35421081,
        "label": 1,
        "sl_max": 3.741,
        "cost_max": 1.86,
        "id": "87bdc9bd82a548f8ac414d264da4e226"
    },
    {
        "d_p": 10501811,
        "d_s": 42532454,
        "label": 0,
        "sl_max": 2.728,
        "cost_max": 2.333,
        "id": "5f66185c7204464bbfdd3612dae609ae"
    },
    {
        "d_p": 14533764,
        "d_s": 2475646,
        "label": 1,
        "sl_max": 1.253,
        "cost_max": 0.329,
        "id": "b41f1bf6822443a78f8930f1a8c45786"
    },
    {
        "d_p": 34782202,
        "d_s": 43225270,
        "label": 1,
        "sl_max": 6.151,
        "cost_max": 2.32,
        "id": "9fdf7b39db574d10b22318c15beb9713"
    },
    {
        "d_p": 45268444,
        "d_s": 24591553,
        "label": 0,
        "sl_max": 4.35,
        "cost_max": 2.382,
        "id": "5671e2f1bb674daa81a206b078500753"
    },
    {
        "d_p": 30294004,
        "d_s": 38614785,
        "label": 0,
        "sl_max": 5.322,
        "cost_max": 2.714,
        "id": "8c260470effe40509f1bd794be365aa5"
    },
    {
        "d_p": 17060744,
        "d_s": 296664,
        "label": 1,
        "sl_max": 1.341,
        "cost_max": 0.516,
        "id": "69eeb1741a354139884a06bb3916aa69"
    },
    {
        "d_p": 32648001,
        "d_s": 11608775,
        "label": 1,
        "sl_max": 2.694,
        "cost_max": 0.958,
        "id": "59f32e521080417ab9eb8ce25b05c36f"
    },
    {
        "d_p": 23512082,
        "d_s": 30412211,
        "label": 0,
        "sl_max": 4.162,
        "cost_max": 1.265,
        "id": "3f71600acc7440c3996ae3681844d883"
    },
    {
        "d_p": 12603296,
        "d_s": 21201445,
        "label": 0,
        "sl_max": 1.414,
        "cost_max": 1.414,
        "id": "60117dbd028542789fa5ae4e03750e4e"
    },
    {
        "d_p": 30294280,
        "d_s": 17611849,
        "label": 1,
        "sl_max": 2.018,
        "cost_max": 1.553,
        "id": "21d019949de24eb89f95cf840de61ff4"
    },
    {
        "d_p": 11855928,
        "d_s": 7644273,
        "label": 1,
        "sl_max": 1.551,
        "cost_max": 0.389,
        "id": "8f62c8d2d36a497589765843a64b04fb"
    },
    {
        "d_p": 31101883,
        "d_s": 47006131,
        "label": 1,
        "sl_max": 5.61,
        "cost_max": 3.25,
        "id": "958ab6065ca048f2b101ec15e06e6150"
    },
    {
        "d_p": 39746367,
        "d_s": 27084035,
        "label": 1,
        "sl_max": 3.98,
        "cost_max": 2.284,
        "id": "be15a9cc06704216b4a6ac33628d7faa"
    },
    {
        "d_p": 44887548,
        "d_s": 3726539,
        "label": 0,
        "sl_max": 2.048,
        "cost_max": 1.043,
        "id": "73aa273e4f324baa8c7afbfe6cf5e7e1"
    },
    {
        "d_p": 15187463,
        "d_s": 23727013,
        "label": 1,
        "sl_max": 2.656,
        "cost_max": 0.885,
        "id": "fb9866bce7d845bea76e3768cdc87f25"
    },
    {
        "d_p": 22694644,
        "d_s": 13828344,
        "label": 0,
        "sl_max": 1.718,
        "cost_max": 1.245,
        "id": "a1c016de531f4837aed2a4017586dd4f"
    },
    {
        "d_p": 35493325,
        "d_s": 42044019,
        "label": 0,
        "sl_max": 4.982,
        "cost_max": 2.968,
        "id": "27d04abee55047a188dea6edbce6598f"
    },
    {
        "d_p": 21102124,
        "d_s": 6941991,
        "label": 0,
        "sl_max": 1.349,
        "cost_max": 0.941,
        "id": "d4e2f1533f8e409c99827ca38862412a"
    },
    {
        "d_p": 16079841,
        "d_s": 33816907,
        "label": 1,
        "sl_max": 3.43,
        "cost_max": 1.425,
        "id": "a20de24d7587463f9744128e860e5144"
    },
    {
        "d_p": 12660467,
        "d_s": 10156140,
        "label": 1,
        "sl_max": 1.464,
        "cost_max": 0.749,
        "id": "82366031cb644b508ecdedb55fc394cf"
    },
    {
        "d_p": 25345757,
        "d_s": 37633086,
        "label": 1,
        "sl_max": 4.689,
        "cost_max": 2.513,
        "id": "86f3e35b834f44c58d81d89645d6d40e"
    },
    {
        "d_p": 35316465,
        "d_s": 8795,
        "label": 0,
        "sl_max": 1.495,
        "cost_max": 0.963,
        "id": "0470445e39f14d1d9e9264051c8dc65a"
    },
    {
        "d_p": 38241404,
        "d_s": 29695042,
        "label": 0,
        "sl_max": 5.342,
        "cost_max": 1.649,
        "id": "c63730c3153f498398cbfea573beb77a"
    }
]